LICENSE
README.md
setup.py
snha4py/Snha.py
snha4py/SnhaDataGen.py
snha4py/SnhaDir.py
snha4py/SnhaNewGraph.py
snha4py/SnhaPlot.py
snha4py/__init__.py
snha4py/__main__.py
snha4py.egg-info/PKG-INFO
snha4py.egg-info/SOURCES.txt
snha4py.egg-info/dependency_links.txt
snha4py.egg-info/requires.txt
snha4py.egg-info/top_level.txt