Metadata-Version: 2.1
Name: snha4py
Version: 0.0.1
Summary: St. Nicholas House algorithm for Python
Home-page: https://github.com/thake93/snha4py
Author: Tim Hake
Author-email: timhake@icloud.com
License: MIT License
Project-URL: Documentation, https://htmlpreview.github.io/?https://github.com/thake93/snha4py/blob/main/docs/__init__.html
License-File: LICENSE
